{
  "urls": {
    "corp:83189:course:lcITU": {
      "url": "https://job.mynavi.jp/28/pc/corpinfo/displayInternship/index?corpId=83189&optNo=lcITU",
      "last_discovered": "2026-07-18T12:20:08+09:00",
      "last_checked": "2026-07-18T13:05:10+09:00",
      "status": "open",
      "transport_available": false,
      "science_only": false
    },
    "corp:84918:course:HfkP6": {
      "url": "https://job.mynavi.jp/28/pc/corpinfo/displayInternship/index?corpId=84918&optNo=HfkP6",
      "last_discovered": "2026-07-18T12:20:08+09:00",
      "last_checked": "2026-07-18T13:05:18+09:00",
      "status": "open",
      "transport_available": false,
      "science_only": false
    },
    "corp:64750:course:FKblo": {
      "url": "https://job.mynavi.jp/28/pc/corpinfo/displayInternship/index?corpId=64750&optNo=FKblo",
      "last_discovered": "2026-07-18T12:20:08+09:00",
      "last_checked": "2026-07-18T13:04:03+09:00",
      "status": "open",
      "transport_available": true,
      "science_only": true
    },
    "corp:52962:course:in5o1": {
      "url": "https://job.mynavi.jp/28/pc/corpinfo/displayInternship/index?corpId=52962&optNo=in5o1",
      "last_discovered": "2026-07-18T12:20:08+09:00",
      "last_checked": "2026-07-18T13:03:27+09:00",
      "status": "open",
      "transport_available": false,
      "science_only": false
    },
    "corp:293013:course:ftTSl": {
      "url": "https://job.mynavi.jp/28/pc/corpinfo/displayInternship/index?corpId=293013&optNo=ftTSl",
      "last_discovered": "2026-07-18T12:20:08+09:00",
      "last_checked": "2026-07-18T13:03:05+09:00",
      "status": "open",
      "transport_available": true,
      "science_only": true
    },
    "corp:82877:course:t9Q1f": {
      "url": "https://job.mynavi.jp/28/pc/corpinfo/displayInternship/index?corpId=82877&optNo=t9Q1f",
      "last_discovered": "2026-07-18T12:20:08+09:00",
      "last_checked": "2026-07-18T13:05:03+09:00",
      "status": "open",
      "transport_available": true,
      "science_only": false
    },
    "corp:239815:course:ZFhSa": {
      "url": "https://job.mynavi.jp/28/pc/corpinfo/displayInternship/index?corpId=239815&optNo=ZFhSa",
      "last_discovered": "2026-07-18T12:20:08+09:00",
      "last_checked": "2026-07-18T13:02:48+09:00",
      "status": "open",
      "transport_available": true,
      "science_only": false
    },
    "corp:201388:course:GvXwp": {
      "url": "https://job.mynavi.jp/28/pc/corpinfo/displayInternship/index?corpId=201388&optNo=GvXwp",
      "last_discovered": "2026-07-18T12:20:08+09:00",
      "last_checked": "2026-07-18T13:02:23+09:00",
      "status": "open",
      "transport_available": true,
      "science_only": true
    },
    "corp:201388:course:xpMJ7": {
      "url": "https://job.mynavi.jp/28/pc/corpinfo/displayInternship/index?corpId=201388&optNo=xpMJ7",
      "last_discovered": "2026-07-18T12:20:08+09:00",
      "last_checked": "2026-07-18T13:02:24+09:00",
      "status": "open",
      "transport_available": true,
      "science_only": true
    },
    "corp:201388:course:6EXCV": {
      "url": "https://job.mynavi.jp/28/pc/corpinfo/displayInternship/index?corpId=201388&optNo=6EXCV",
      "last_discovered": "2026-07-18T12:20:08+09:00",
      "last_checked": "2026-07-18T13:02:21+09:00",
      "status": "open",
      "transport_available": true,
      "science_only": true
    },
    "corp:72972:course:YMgYf": {
      "url": "https://job.mynavi.jp/28/pc/corpinfo/displayInternship/index?corpId=72972&optNo=YMgYf",
      "last_discovered": "2026-07-18T12:20:08+09:00",
      "last_checked": "2026-07-18T13:04:41+09:00",
      "status": "closed",
      "transport_available": true,
      "science_only": false
    },
    "corp:105247:course:wGeZ1": {
      "url": "https://job.mynavi.jp/28/pc/corpinfo/displayInternship/index?corpId=105247&optNo=wGeZ1",
      "last_discovered": "2026-07-18T12:20:08+09:00",
      "last_checked": "2026-07-18T13:02:04+09:00",
      "status": "closed",
      "transport_available": false,
      "science_only": false
    },
    "corp:351:course:kxjzd": {
      "url": "https://job.mynavi.jp/28/pc/corpinfo/displayInternship/index?corpId=351&optNo=kxjzd",
      "last_discovered": "2026-07-18T12:20:08+09:00",
      "last_checked": "2026-07-18T13:03:09+09:00",
      "status": "open",
      "transport_available": false,
      "science_only": false
    },
    "corp:204:course:gea5X": {
      "url": "https://job.mynavi.jp/28/pc/corpinfo/displayInternship/index?corpId=204&optNo=gea5X",
      "last_discovered": "2026-07-18T12:20:08+09:00",
      "last_checked": "2026-07-18T13:02:36+09:00",
      "status": "open",
      "transport_available": false,
      "science_only": false
    },
    "corp:70580:course:IOXE2": {
      "url": "https://job.mynavi.jp/28/pc/corpinfo/displayInternship/index?corpId=70580&optNo=IOXE2",
      "last_discovered": "2026-07-18T12:20:08+09:00",
      "last_checked": "2026-07-18T13:04:27+09:00",
      "status": "open",
      "transport_available": true,
      "science_only": true
    },
    "corp:56660:course:ngaLz": {
      "url": "https://job.mynavi.jp/28/pc/corpinfo/displayInternship/index?corpId=56660&optNo=ngaLz",
      "last_discovered": "2026-07-18T12:20:08+09:00",
      "last_checked": "2026-07-18T13:03:46+09:00",
      "status": "open",
      "transport_available": true,
      "science_only": false
    },
    "corp:56660:course:HmBap": {
      "url": "https://job.mynavi.jp/28/pc/corpinfo/displayInternship/index?corpId=56660&optNo=HmBap",
      "last_discovered": "2026-07-18T12:20:08+09:00",
      "last_checked": "2026-07-18T13:03:44+09:00",
      "status": "open",
      "transport_available": true,
      "science_only": false
    },
    "corp:70726:course:U-75l": {
      "url": "https://job.mynavi.jp/28/pc/corpinfo/displayInternship/index?corpId=70726&optNo=U-75l",
      "last_discovered": "2026-07-18T12:20:08+09:00",
      "last_checked": "2026-07-18T13:04:29+09:00",
      "status": "open",
      "transport_available": false,
      "science_only": false
    },
    "corp:106493:course:26Bm2": {
      "url": "https://job.mynavi.jp/28/pc/corpinfo/displayInternship/index?corpId=106493&optNo=26Bm2",
      "last_discovered": "2026-07-18T12:20:08+09:00",
      "last_checked": "2026-07-18T13:02:09+09:00",
      "status": "open",
      "transport_available": false,
      "science_only": false
    },
    "corp:72008:course:BVZz0": {
      "url": "https://job.mynavi.jp/28/pc/corpinfo/displayInternship/index?corpId=72008&optNo=BVZz0",
      "last_discovered": "2026-07-18T12:20:08+09:00",
      "last_checked": "2026-07-18T13:04:35+09:00",
      "status": "open",
      "transport_available": true,
      "science_only": true
    },
    "corp:91899:course:r0tTp": {
      "url": "https://job.mynavi.jp/28/pc/corpinfo/displayInternship/index?corpId=91899&optNo=r0tTp",
      "last_discovered": "2026-07-18T12:20:08+09:00",
      "last_checked": "2026-07-18T13:05:32+09:00",
      "status": "open",
      "transport_available": true,
      "science_only": false
    },
    "corp:5849:course:bigvh": {
      "url": "https://job.mynavi.jp/28/pc/corpinfo/displayInternship/index?corpId=5849&optNo=bigvh",
      "last_discovered": "2026-07-18T12:20:08+09:00",
      "last_checked": "2026-07-18T13:03:51+09:00",
      "status": "open",
      "transport_available": true,
      "science_only": false
    },
    "corp:5849:course:N8kpH": {
      "url": "https://job.mynavi.jp/28/pc/corpinfo/displayInternship/index?corpId=5849&optNo=N8kpH",
      "last_discovered": "2026-07-18T12:20:08+09:00",
      "last_checked": "2026-07-18T13:03:49+09:00",
      "status": "open",
      "transport_available": true,
      "science_only": false
    },
    "corp:78010:course:axsff": {
      "url": "https://job.mynavi.jp/28/pc/corpinfo/displayInternship/index?corpId=78010&optNo=axsff",
      "last_discovered": "2026-07-18T12:20:08+09:00",
      "last_checked": "2026-07-18T13:04:56+09:00",
      "status": "open",
      "transport_available": false,
      "science_only": false
    },
    "corp:78010:course:smeaO": {
      "url": "https://job.mynavi.jp/28/pc/corpinfo/displayInternship/index?corpId=78010&optNo=smeaO",
      "last_discovered": "2026-07-18T12:20:08+09:00",
      "last_checked": "2026-07-18T13:05:00+09:00",
      "status": "open",
      "transport_available": false,
      "science_only": false
    },
    "corp:78010:course:kgYhz": {
      "url": "https://job.mynavi.jp/28/pc/corpinfo/displayInternship/index?corpId=78010&optNo=kgYhz",
      "last_discovered": "2026-07-18T12:20:08+09:00",
      "last_checked": "2026-07-18T13:04:58+09:00",
      "status": "closed",
      "transport_available": false,
      "science_only": false
    },
    "corp:73148:course:Gzw0H": {
      "url": "https://job.mynavi.jp/28/pc/corpinfo/displayInternship/index?corpId=73148&optNo=Gzw0H",
      "last_discovered": "2026-07-18T12:20:08+09:00",
      "last_checked": "2026-07-18T13:04:46+09:00",
      "status": "open",
      "transport_available": false,
      "science_only": false
    },
    "corp:57798:course:wXfag": {
      "url": "https://job.mynavi.jp/28/pc/corpinfo/displayInternship/index?corpId=57798&optNo=wXfag",
      "last_discovered": "2026-07-18T12:20:08+09:00",
      "last_checked": "2026-07-18T13:03:47+09:00",
      "status": "open",
      "transport_available": true,
      "science_only": false
    },
    "corp:111185:course:o9NMY": {
      "url": "https://job.mynavi.jp/28/pc/corpinfo/displayInternship/index?corpId=111185&optNo=o9NMY",
      "last_discovered": "2026-07-18T12:20:08+09:00",
      "last_checked": "2026-07-18T13:02:14+09:00",
      "status": "open",
      "transport_available": true,
      "science_only": true
    },
    "corp:5252:course:d8-WV": {
      "url": "https://job.mynavi.jp/28/pc/corpinfo/displayInternship/index?corpId=5252&optNo=d8-WV",
      "last_discovered": "2026-07-18T12:20:08+09:00",
      "last_checked": "2026-07-18T13:03:24+09:00",
      "status": "open",
      "transport_available": true,
      "science_only": false
    },
    "corp:3975:course:aZDi2": {
      "url": "https://job.mynavi.jp/28/pc/corpinfo/displayInternship/index?corpId=3975&optNo=aZDi2",
      "last_discovered": "2026-07-18T12:20:08+09:00",
      "last_checked": "2026-07-18T13:03:14+09:00",
      "status": "open",
      "transport_available": false,
      "science_only": false
    },
    "corp:10635:course:Pvfyz": {
      "url": "https://job.mynavi.jp/28/pc/corpinfo/displayInternship/index?corpId=10635&optNo=Pvfyz",
      "last_discovered": "2026-07-18T12:20:08+09:00",
      "last_checked": "2026-07-18T13:02:07+09:00",
      "status": "open",
      "transport_available": false,
      "science_only": false
    },
    "corp:103628:course:tvkvy": {
      "url": "https://job.mynavi.jp/28/pc/corpinfo/displayInternship/index?corpId=103628&optNo=tvkvy",
      "last_discovered": "2026-07-18T12:20:08+09:00",
      "last_checked": "2026-07-18T13:02:02+09:00",
      "status": "open",
      "transport_available": false,
      "science_only": false
    },
    "corp:98428:course:WQt0O": {
      "url": "https://job.mynavi.jp/28/pc/corpinfo/displayInternship/index?corpId=98428&optNo=WQt0O",
      "last_discovered": "2026-07-18T12:20:08+09:00",
      "last_checked": "2026-07-18T13:05:46+09:00",
      "status": "open",
      "transport_available": true,
      "science_only": false
    },
    "corp:99147:course:wzjwB": {
      "url": "https://job.mynavi.jp/28/pc/corpinfo/displayInternship/index?corpId=99147&optNo=wzjwB",
      "last_discovered": "2026-07-18T12:20:08+09:00",
      "last_checked": "2026-07-18T13:05:49+09:00",
      "status": "open",
      "transport_available": true,
      "science_only": false
    },
    "corp:75262:course:wDsHV": {
      "url": "https://job.mynavi.jp/28/pc/corpinfo/displayInternship/index?corpId=75262&optNo=wDsHV",
      "last_discovered": "2026-07-18T12:20:08+09:00",
      "last_checked": "2026-07-18T13:04:49+09:00",
      "status": "open",
      "transport_available": false,
      "science_only": false
    },
    "corp:105358:course:Zv1DV": {
      "url": "https://job.mynavi.jp/28/pc/corpinfo/displayInternship/index?corpId=105358&optNo=Zv1DV",
      "last_discovered": "2026-07-18T12:20:08+09:00",
      "last_checked": "2026-07-18T13:02:06+09:00",
      "status": "open",
      "transport_available": false,
      "science_only": false
    },
    "corp:75894:course:f7NnQ": {
      "url": "https://job.mynavi.jp/28/pc/corpinfo/displayInternship/index?corpId=75894&optNo=f7NnQ",
      "last_discovered": "2026-07-18T12:20:08+09:00",
      "last_checked": "2026-07-18T13:04:54+09:00",
      "status": "open",
      "transport_available": false,
      "science_only": false
    },
    "corp:75894:course:NnyEd": {
      "url": "https://job.mynavi.jp/28/pc/corpinfo/displayInternship/index?corpId=75894&optNo=NnyEd",
      "last_discovered": "2026-07-18T12:20:08+09:00",
      "last_checked": "2026-07-18T13:04:51+09:00",
      "status": "open",
      "transport_available": true,
      "science_only": false
    },
    "corp:65502:course:ZPB3-": {
      "url": "https://job.mynavi.jp/28/pc/corpinfo/displayInternship/index?corpId=65502&optNo=ZPB3-",
      "last_discovered": "2026-07-18T12:20:08+09:00",
      "last_checked": "2026-07-18T13:04:10+09:00",
      "status": "open",
      "transport_available": false,
      "science_only": false
    },
    "corp:61222:course:D9TMm": {
      "url": "https://job.mynavi.jp/28/pc/corpinfo/displayInternship/index?corpId=61222&optNo=D9TMm",
      "last_discovered": "2026-07-18T12:20:08+09:00",
      "last_checked": "2026-07-18T13:04:00+09:00",
      "status": "open",
      "transport_available": false,
      "science_only": false
    },
    "corp:61222:course:yg-Rv": {
      "url": "https://job.mynavi.jp/28/pc/corpinfo/displayInternship/index?corpId=61222&optNo=yg-Rv",
      "last_discovered": "2026-07-18T12:20:08+09:00",
      "last_checked": "2026-07-18T13:04:02+09:00",
      "status": "open",
      "transport_available": false,
      "science_only": false
    },
    "corp:263680:course:HkEA3": {
      "url": "https://job.mynavi.jp/28/pc/corpinfo/displayInternship/index?corpId=263680&optNo=HkEA3",
      "last_discovered": "2026-07-18T12:20:08+09:00",
      "last_checked": "2026-07-18T13:02:57+09:00",
      "status": "open",
      "transport_available": false,
      "science_only": false
    },
    "corp:94150:course:93Ohv": {
      "url": "https://job.mynavi.jp/28/pc/corpinfo/displayInternship/index?corpId=94150&optNo=93Ohv",
      "last_discovered": "2026-07-18T12:20:08+09:00",
      "last_checked": "2026-07-18T13:05:34+09:00",
      "status": "open",
      "transport_available": false,
      "science_only": false
    },
    "corp:53017:course:VlHOV": {
      "url": "https://job.mynavi.jp/28/pc/corpinfo/displayInternship/index?corpId=53017&optNo=VlHOV",
      "last_discovered": "2026-07-18T12:20:08+09:00",
      "last_checked": "2026-07-18T13:03:29+09:00",
      "status": "open",
      "transport_available": false,
      "science_only": false
    },
    "corp:87518:course:we3As": {
      "url": "https://job.mynavi.jp/28/pc/corpinfo/displayInternship/index?corpId=87518&optNo=we3As",
      "last_discovered": "2026-07-18T12:20:08+09:00",
      "last_checked": "2026-07-18T13:05:29+09:00",
      "status": "open",
      "transport_available": false,
      "science_only": false
    },
    "corp:87518:course:ozu2Q": {
      "url": "https://job.mynavi.jp/28/pc/corpinfo/displayInternship/index?corpId=87518&optNo=ozu2Q",
      "last_discovered": "2026-07-18T12:20:08+09:00",
      "last_checked": "2026-07-18T13:05:25+09:00",
      "status": "open",
      "transport_available": false,
      "science_only": false
    },
    "corp:87518:course:qLIgH": {
      "url": "https://job.mynavi.jp/28/pc/corpinfo/displayInternship/index?corpId=87518&optNo=qLIgH",
      "last_discovered": "2026-07-18T12:20:08+09:00",
      "last_checked": "2026-07-18T13:05:27+09:00",
      "status": "open",
      "transport_available": false,
      "science_only": false
    },
    "corp:83189:course:gxAs6": {
      "url": "https://job.mynavi.jp/28/pc/corpinfo/displayInternship/index?corpId=83189&optNo=gxAs6",
      "last_discovered": "2026-07-18T12:20:08+09:00",
      "last_checked": "2026-07-18T13:05:08+09:00",
      "status": "open",
      "transport_available": false,
      "science_only": false
    },
    "corp:83189:course:4-zXz": {
      "url": "https://job.mynavi.jp/28/pc/corpinfo/displayInternship/index?corpId=83189&optNo=4-zXz",
      "last_discovered": "2026-07-18T12:20:08+09:00",
      "last_checked": "2026-07-18T13:05:06+09:00",
      "status": "open",
      "transport_available": false,
      "science_only": false
    },
    "corp:84918:course:F3obf": {
      "url": "https://job.mynavi.jp/28/pc/corpinfo/displayInternship/index?corpId=84918&optNo=F3obf",
      "last_discovered": "2026-07-18T12:20:08+09:00",
      "last_checked": "2026-07-18T13:05:17+09:00",
      "status": "open",
      "transport_available": false,
      "science_only": false
    },
    "corp:64750:course:WUBqY": {
      "url": "https://job.mynavi.jp/28/pc/corpinfo/displayInternship/index?corpId=64750&optNo=WUBqY",
      "last_discovered": "2026-07-18T12:20:08+09:00",
      "last_checked": "2026-07-18T13:04:05+09:00",
      "status": "open",
      "transport_available": true,
      "science_only": false
    },
    "corp:64750:course:Zu6dB": {
      "url": "https://job.mynavi.jp/28/pc/corpinfo/displayInternship/index?corpId=64750&optNo=Zu6dB",
      "last_discovered": "2026-07-18T12:20:08+09:00",
      "last_checked": "2026-07-18T13:04:07+09:00",
      "status": "open",
      "transport_available": true,
      "science_only": true
    },
    "corp:68756:course:5JXwO": {
      "url": "https://job.mynavi.jp/28/pc/corpinfo/displayInternship/index?corpId=68756&optNo=5JXwO",
      "last_discovered": "2026-07-18T12:20:08+09:00",
      "last_checked": "2026-07-18T13:04:15+09:00",
      "status": "open",
      "transport_available": false,
      "science_only": false
    },
    "corp:68756:course:zwnta": {
      "url": "https://job.mynavi.jp/28/pc/corpinfo/displayInternship/index?corpId=68756&optNo=zwnta",
      "last_discovered": "2026-07-18T12:20:08+09:00",
      "last_checked": "2026-07-18T13:04:19+09:00",
      "status": "open",
      "transport_available": false,
      "science_only": false
    },
    "corp:1889:course:Oelc2": {
      "url": "https://job.mynavi.jp/28/pc/corpinfo/displayInternship/index?corpId=1889&optNo=Oelc2",
      "last_discovered": "2026-07-18T12:20:08+09:00",
      "last_checked": "2026-07-18T13:02:18+09:00",
      "status": "open",
      "transport_available": false,
      "science_only": false
    },
    "corp:203781:course:5HKVO": {
      "url": "https://job.mynavi.jp/28/pc/corpinfo/displayInternship/index?corpId=203781&optNo=5HKVO",
      "last_discovered": "2026-07-18T12:20:08+09:00",
      "last_checked": "2026-07-18T13:02:28+09:00",
      "status": "open",
      "transport_available": true,
      "science_only": false
    },
    "corp:203781:course:DfoRa": {
      "url": "https://job.mynavi.jp/28/pc/corpinfo/displayInternship/index?corpId=203781&optNo=DfoRa",
      "last_discovered": "2026-07-18T12:20:08+09:00",
      "last_checked": "2026-07-18T13:02:31+09:00",
      "status": "open",
      "transport_available": true,
      "science_only": false
    },
    "corp:203781:course:bFzhV": {
      "url": "https://job.mynavi.jp/28/pc/corpinfo/displayInternship/index?corpId=203781&optNo=bFzhV",
      "last_discovered": "2026-07-18T12:20:08+09:00",
      "last_checked": "2026-07-18T13:02:35+09:00",
      "status": "open",
      "transport_available": true,
      "science_only": false
    },
    "corp:52962:course:amaN-": {
      "url": "https://job.mynavi.jp/28/pc/corpinfo/displayInternship/index?corpId=52962&optNo=amaN-",
      "last_discovered": "2026-07-18T12:20:08+09:00",
      "last_checked": "2026-07-18T13:03:25+09:00",
      "status": "open",
      "transport_available": false,
      "science_only": false
    },
    "corp:214558:course:Do8YB": {
      "url": "https://job.mynavi.jp/28/pc/corpinfo/displayInternship/index?corpId=214558&optNo=Do8YB",
      "last_discovered": "2026-07-18T12:20:08+09:00",
      "last_checked": "2026-07-18T13:02:43+09:00",
      "status": "closed",
      "transport_available": false,
      "science_only": false
    },
    "corp:214558:course:WGLRB": {
      "url": "https://job.mynavi.jp/28/pc/corpinfo/displayInternship/index?corpId=214558&optNo=WGLRB",
      "last_discovered": "2026-07-18T12:20:08+09:00",
      "last_checked": "2026-07-18T13:02:45+09:00",
      "status": "open",
      "transport_available": false,
      "science_only": false
    },
    "corp:214558:course:nCzqz": {
      "url": "https://job.mynavi.jp/28/pc/corpinfo/displayInternship/index?corpId=214558&optNo=nCzqz",
      "last_discovered": "2026-07-18T12:20:08+09:00",
      "last_checked": "2026-07-18T13:02:47+09:00",
      "status": "open",
      "transport_available": false,
      "science_only": false
    },
    "corp:293013:course:A6NO3": {
      "url": "https://job.mynavi.jp/28/pc/corpinfo/displayInternship/index?corpId=293013&optNo=A6NO3",
      "last_discovered": "2026-07-18T12:20:08+09:00",
      "last_checked": "2026-07-18T13:03:00+09:00",
      "status": "open",
      "transport_available": true,
      "science_only": true
    },
    "corp:293013:course:1F9H2": {
      "url": "https://job.mynavi.jp/28/pc/corpinfo/displayInternship/index?corpId=293013&optNo=1F9H2",
      "last_discovered": "2026-07-18T12:20:08+09:00",
      "last_checked": "2026-07-18T13:02:58+09:00",
      "status": "open",
      "transport_available": false,
      "science_only": false
    },
    "corp:293013:course:tP6aI": {
      "url": "https://job.mynavi.jp/28/pc/corpinfo/displayInternship/index?corpId=293013&optNo=tP6aI",
      "last_discovered": "2026-07-18T12:20:08+09:00",
      "last_checked": "2026-07-18T13:03:07+09:00",
      "status": "open",
      "transport_available": true,
      "science_only": true
    },
    "corp:82877:course:vkKRz": {
      "url": "https://job.mynavi.jp/28/pc/corpinfo/displayInternship/index?corpId=82877&optNo=vkKRz",
      "last_discovered": "2026-07-18T12:20:08+09:00",
      "last_checked": "2026-07-18T13:05:05+09:00",
      "status": "open",
      "transport_available": true,
      "science_only": false
    },
    "corp:82877:course:rT9Yt": {
      "url": "https://job.mynavi.jp/28/pc/corpinfo/displayInternship/index?corpId=82877&optNo=rT9Yt",
      "last_discovered": "2026-07-18T12:20:08+09:00",
      "last_checked": "2026-07-18T13:05:01+09:00",
      "status": "open",
      "transport_available": true,
      "science_only": false
    },
    "corp:95445:course:BI8Tz": {
      "url": "https://job.mynavi.jp/28/pc/corpinfo/displayInternship/index?corpId=95445&optNo=BI8Tz",
      "last_discovered": "2026-07-18T12:20:08+09:00",
      "last_checked": "2026-07-18T13:05:37+09:00",
      "status": "open",
      "transport_available": false,
      "science_only": false
    },
    "corp:95445:course:V0z4W": {
      "url": "https://job.mynavi.jp/28/pc/corpinfo/displayInternship/index?corpId=95445&optNo=V0z4W",
      "last_discovered": "2026-07-18T12:20:08+09:00",
      "last_checked": "2026-07-18T13:05:41+09:00",
      "status": "open",
      "transport_available": false,
      "science_only": false
    },
    "corp:95445:course:ea1Hn": {
      "url": "https://job.mynavi.jp/28/pc/corpinfo/displayInternship/index?corpId=95445&optNo=ea1Hn",
      "last_discovered": "2026-07-18T12:20:08+09:00",
      "last_checked": "2026-07-18T13:05:44+09:00",
      "status": "open",
      "transport_available": false,
      "science_only": false
    },
    "corp:460:course:Xip61": {
      "url": "https://job.mynavi.jp/28/pc/corpinfo/displayInternship/index?corpId=460&optNo=Xip61",
      "last_discovered": "2026-07-18T12:20:08+09:00",
      "last_checked": "2026-07-18T13:03:17+09:00",
      "status": "open",
      "transport_available": true,
      "science_only": true
    },
    "corp:84252:course:nM1fd": {
      "url": "https://job.mynavi.jp/28/pc/corpinfo/displayInternship/index?corpId=84252&optNo=nM1fd",
      "last_discovered": "2026-07-18T12:20:08+09:00",
      "last_checked": "2026-07-18T13:05:15+09:00",
      "status": "open",
      "transport_available": false,
      "science_only": false
    },
    "corp:39009:course:WDuHd": {
      "url": "https://job.mynavi.jp/28/pc/corpinfo/displayInternship/index?corpId=39009&optNo=WDuHd",
      "last_discovered": "2026-07-18T12:20:08+09:00",
      "last_checked": "2026-07-18T13:03:12+09:00",
      "status": "cancelled",
      "transport_available": false,
      "science_only": false
    },
    "corp:39009:course:5banY": {
      "url": "https://job.mynavi.jp/28/pc/corpinfo/displayInternship/index?corpId=39009&optNo=5banY",
      "last_discovered": "2026-07-18T12:20:08+09:00",
      "last_checked": "2026-07-18T13:03:10+09:00",
      "status": "cancelled",
      "transport_available": false,
      "science_only": false
    },
    "corp:25133:course:4IiK-": {
      "url": "https://job.mynavi.jp/28/pc/corpinfo/displayInternship/index?corpId=25133&optNo=4IiK-",
      "last_discovered": "2026-07-18T12:20:08+09:00",
      "last_checked": "2026-07-18T13:02:53+09:00",
      "status": "open",
      "transport_available": false,
      "science_only": false
    },
    "corp:70547:course:Qrrp1": {
      "url": "https://job.mynavi.jp/28/pc/corpinfo/displayInternship/index?corpId=70547&optNo=Qrrp1",
      "last_discovered": "2026-07-18T12:20:08+09:00",
      "last_checked": "2026-07-18T13:04:24+09:00",
      "status": "open",
      "transport_available": true,
      "science_only": false
    },
    "corp:56242:course:e6p3U": {
      "url": "https://job.mynavi.jp/28/pc/corpinfo/displayInternship/index?corpId=56242&optNo=e6p3U",
      "last_discovered": "2026-07-18T12:20:08+09:00",
      "last_checked": "2026-07-18T13:03:41+09:00",
      "status": "open",
      "transport_available": false,
      "science_only": false
    },
    "corp:239815:course:gT5bD": {
      "url": "https://job.mynavi.jp/28/pc/corpinfo/displayInternship/index?corpId=239815&optNo=gT5bD",
      "last_discovered": "2026-07-18T12:20:08+09:00",
      "last_checked": "2026-07-18T13:02:50+09:00",
      "status": "open",
      "transport_available": false,
      "science_only": false
    },
    "corp:532:course:LEgcv": {
      "url": "https://job.mynavi.jp/28/pc/corpinfo/displayInternship/index?corpId=532&optNo=LEgcv",
      "last_discovered": "2026-07-18T12:20:08+09:00",
      "last_checked": "2026-07-18T13:03:32+09:00",
      "status": "open",
      "transport_available": false,
      "science_only": true
    },
    "corp:532:course:9Sa-H": {
      "url": "https://job.mynavi.jp/28/pc/corpinfo/displayInternship/index?corpId=532&optNo=9Sa-H",
      "last_discovered": "2026-07-18T12:20:08+09:00",
      "last_checked": "2026-07-18T13:03:30+09:00",
      "status": "open",
      "transport_available": false,
      "science_only": true
    },
    "corp:59411:course:-mdkv": {
      "url": "https://job.mynavi.jp/28/pc/corpinfo/displayInternship/index?corpId=59411&optNo=-mdkv",
      "last_discovered": "2026-07-18T12:20:08+09:00",
      "last_checked": "2026-07-18T13:03:53+09:00",
      "status": "open",
      "transport_available": false,
      "science_only": false
    },
    "corp:59411:course:aI9ll": {
      "url": "https://job.mynavi.jp/28/pc/corpinfo/displayInternship/index?corpId=59411&optNo=aI9ll",
      "last_discovered": "2026-07-18T12:20:08+09:00",
      "last_checked": "2026-07-18T13:03:58+09:00",
      "status": "open",
      "transport_available": false,
      "science_only": false
    },
    "corp:59411:course:Dtkoo": {
      "url": "https://job.mynavi.jp/28/pc/corpinfo/displayInternship/index?corpId=59411&optNo=Dtkoo",
      "last_discovered": "2026-07-18T12:20:08+09:00",
      "last_checked": "2026-07-18T13:03:54+09:00",
      "status": "open",
      "transport_available": false,
      "science_only": false
    },
    "corp:3988:course:ljtVO": {
      "url": "https://job.mynavi.jp/28/pc/corpinfo/displayInternship/index?corpId=3988&optNo=ljtVO",
      "last_discovered": "2026-07-18T12:20:08+09:00",
      "last_checked": "2026-07-18T13:03:15+09:00",
      "status": "open",
      "transport_available": false,
      "science_only": false
    },
    "corp:109648:course:HVyFQ": {
      "url": "https://job.mynavi.jp/28/pc/corpinfo/displayInternship/index?corpId=109648&optNo=HVyFQ",
      "last_discovered": "2026-07-18T12:20:08+09:00",
      "last_checked": "2026-07-18T13:02:11+09:00",
      "status": "open",
      "transport_available": false,
      "science_only": false
    },
    "corp:75894:course:VJAM6": {
      "url": "https://job.mynavi.jp/28/pc/corpinfo/displayInternship/index?corpId=75894&optNo=VJAM6",
      "last_discovered": "2026-07-18T12:20:08+09:00",
      "last_checked": "2026-07-18T13:04:52+09:00",
      "status": "open",
      "transport_available": false,
      "science_only": false
    },
    "corp:263680:course:8tXp3": {
      "url": "https://job.mynavi.jp/28/pc/corpinfo/displayInternship/index?corpId=263680&optNo=8tXp3",
      "last_discovered": "2026-07-18T12:20:08+09:00",
      "last_checked": "2026-07-18T13:02:55+09:00",
      "status": "open",
      "transport_available": false,
      "science_only": false
    },
    "corp:94150:course:Ui46X": {
      "url": "https://job.mynavi.jp/28/pc/corpinfo/displayInternship/index?corpId=94150&optNo=Ui46X",
      "last_discovered": "2026-07-18T12:20:08+09:00",
      "last_checked": "2026-07-18T13:05:36+09:00",
      "status": "open",
      "transport_available": false,
      "science_only": false
    },
    "corp:50041:course:h2vD6": {
      "url": "https://job.mynavi.jp/28/pc/corpinfo/displayInternship/index?corpId=50041&optNo=h2vD6",
      "last_discovered": "2026-07-18T12:20:08+09:00",
      "last_checked": "2026-07-18T13:03:22+09:00",
      "status": "open",
      "transport_available": false,
      "science_only": false
    },
    "corp:50041:course:Ows6X": {
      "url": "https://job.mynavi.jp/28/pc/corpinfo/displayInternship/index?corpId=50041&optNo=Ows6X",
      "last_discovered": "2026-07-18T12:20:08+09:00",
      "last_checked": "2026-07-18T13:03:20+09:00",
      "status": "open",
      "transport_available": true,
      "science_only": false
    },
    "corp:87518:course:xzmyz": {
      "url": "https://job.mynavi.jp/28/pc/corpinfo/displayInternship/index?corpId=87518&optNo=xzmyz",
      "last_discovered": "2026-07-18T12:20:08+09:00",
      "last_checked": "2026-07-18T13:05:30+09:00",
      "status": "open",
      "transport_available": false,
      "science_only": false
    },
    "corp:87518:course:jH-sz": {
      "url": "https://job.mynavi.jp/28/pc/corpinfo/displayInternship/index?corpId=87518&optNo=jH-sz",
      "last_discovered": "2026-07-18T12:20:08+09:00",
      "last_checked": "2026-07-18T13:05:24+09:00",
      "status": "open",
      "transport_available": false,
      "science_only": false
    },
    "corp:87518:course:EYbPW": {
      "url": "https://job.mynavi.jp/28/pc/corpinfo/displayInternship/index?corpId=87518&optNo=EYbPW",
      "last_discovered": "2026-07-18T12:20:08+09:00",
      "last_checked": "2026-07-18T13:05:22+09:00",
      "status": "open",
      "transport_available": false,
      "science_only": false
    },
    "corp:83189:course:rpKNQ": {
      "url": "https://job.mynavi.jp/28/pc/corpinfo/displayInternship/index?corpId=83189&optNo=rpKNQ",
      "last_discovered": "2026-07-18T12:20:08+09:00",
      "last_checked": "2026-07-18T13:05:11+09:00",
      "status": "open",
      "transport_available": false,
      "science_only": false
    },
    "corp:84918:course:ODcxq": {
      "url": "https://job.mynavi.jp/28/pc/corpinfo/displayInternship/index?corpId=84918&optNo=ODcxq",
      "last_discovered": "2026-07-18T12:20:08+09:00",
      "last_checked": "2026-07-18T13:05:20+09:00",
      "status": "closed",
      "transport_available": false,
      "science_only": false
    },
    "corp:64750:course:hApNt": {
      "url": "https://job.mynavi.jp/28/pc/corpinfo/displayInternship/index?corpId=64750&optNo=hApNt",
      "last_discovered": "2026-07-18T12:20:08+09:00",
      "last_checked": "2026-07-18T13:04:08+09:00",
      "status": "closed",
      "transport_available": false,
      "science_only": false
    },
    "corp:206616:course:n7TH7": {
      "url": "https://job.mynavi.jp/28/pc/corpinfo/displayInternship/index?corpId=206616&optNo=n7TH7",
      "last_discovered": "2026-07-18T12:20:08+09:00",
      "last_checked": "2026-07-18T13:02:40+09:00",
      "status": "open",
      "transport_available": false,
      "science_only": false
    },
    "corp:206616:course:GYRnI": {
      "url": "https://job.mynavi.jp/28/pc/corpinfo/displayInternship/index?corpId=206616&optNo=GYRnI",
      "last_discovered": "2026-07-18T12:20:08+09:00",
      "last_checked": "2026-07-18T13:02:38+09:00",
      "status": "open",
      "transport_available": false,
      "science_only": false
    },
    "corp:68756:course:HrcGy": {
      "url": "https://job.mynavi.jp/28/pc/corpinfo/displayInternship/index?corpId=68756&optNo=HrcGy",
      "last_discovered": "2026-07-18T12:20:08+09:00",
      "last_checked": "2026-07-18T13:04:17+09:00",
      "status": "open",
      "transport_available": false,
      "science_only": false
    },
    "corp:1889:course:L79HY": {
      "url": "https://job.mynavi.jp/28/pc/corpinfo/displayInternship/index?corpId=1889&optNo=L79HY",
      "last_discovered": "2026-07-18T12:20:08+09:00",
      "last_checked": "2026-07-18T13:02:16+09:00",
      "status": "open",
      "transport_available": false,
      "science_only": false
    },
    "corp:1889:course:ktp-V": {
      "url": "https://job.mynavi.jp/28/pc/corpinfo/displayInternship/index?corpId=1889&optNo=ktp-V",
      "last_discovered": "2026-07-18T12:20:08+09:00",
      "last_checked": "2026-07-18T13:02:19+09:00",
      "status": "closed",
      "transport_available": false,
      "science_only": false
    },
    "corp:203781:course:JpEJ6": {
      "url": "https://job.mynavi.jp/28/pc/corpinfo/displayInternship/index?corpId=203781&optNo=JpEJ6",
      "last_discovered": "2026-07-18T12:20:08+09:00",
      "last_checked": "2026-07-18T13:02:33+09:00",
      "status": "open",
      "transport_available": false,
      "science_only": false
    },
    "corp:203781:course:6UQa7": {
      "url": "https://job.mynavi.jp/28/pc/corpinfo/displayInternship/index?corpId=203781&optNo=6UQa7",
      "last_discovered": "2026-07-18T12:20:08+09:00",
      "last_checked": "2026-07-18T13:02:30+09:00",
      "status": "open",
      "transport_available": false,
      "science_only": false
    },
    "corp:72837:course:uk934": {
      "url": "https://job.mynavi.jp/28/pc/corpinfo/displayInternship/index?corpId=72837&optNo=uk934",
      "last_discovered": "2026-07-18T12:20:08+09:00",
      "last_checked": "2026-07-18T13:04:39+09:00",
      "status": "open",
      "transport_available": false,
      "science_only": false
    },
    "corp:72837:course:h7L16": {
      "url": "https://job.mynavi.jp/28/pc/corpinfo/displayInternship/index?corpId=72837&optNo=h7L16",
      "last_discovered": "2026-07-18T12:20:08+09:00",
      "last_checked": "2026-07-18T13:04:37+09:00",
      "status": "open",
      "transport_available": false,
      "science_only": false
    },
    "corp:214558:course:6wRcV": {
      "url": "https://job.mynavi.jp/28/pc/corpinfo/displayInternship/index?corpId=214558&optNo=6wRcV",
      "last_discovered": "2026-07-18T12:20:08+09:00",
      "last_checked": "2026-07-18T13:02:41+09:00",
      "status": "open",
      "transport_available": false,
      "science_only": true
    },
    "corp:293013:course:AKyi6": {
      "url": "https://job.mynavi.jp/28/pc/corpinfo/displayInternship/index?corpId=293013&optNo=AKyi6",
      "last_discovered": "2026-07-18T12:20:08+09:00",
      "last_checked": "2026-07-18T13:03:02+09:00",
      "status": "open",
      "transport_available": false,
      "science_only": false
    },
    "corp:293013:course:W1uis": {
      "url": "https://job.mynavi.jp/28/pc/corpinfo/displayInternship/index?corpId=293013&optNo=W1uis",
      "last_discovered": "2026-07-18T12:20:08+09:00",
      "last_checked": "2026-07-18T13:03:04+09:00",
      "status": "open",
      "transport_available": false,
      "science_only": false
    },
    "corp:65967:course:wfiap": {
      "url": "https://job.mynavi.jp/28/pc/corpinfo/displayInternship/index?corpId=65967&optNo=wfiap",
      "last_discovered": "2026-07-18T12:20:08+09:00",
      "last_checked": "2026-07-18T13:04:13+09:00",
      "status": "open",
      "transport_available": false,
      "science_only": false
    },
    "corp:65967:course:VMd6-": {
      "url": "https://job.mynavi.jp/28/pc/corpinfo/displayInternship/index?corpId=65967&optNo=VMd6-",
      "last_discovered": "2026-07-18T12:20:08+09:00",
      "last_checked": "2026-07-18T13:04:12+09:00",
      "status": "open",
      "transport_available": false,
      "science_only": false
    },
    "corp:95445:course:OEr1B": {
      "url": "https://job.mynavi.jp/28/pc/corpinfo/displayInternship/index?corpId=95445&optNo=OEr1B",
      "last_discovered": "2026-07-18T12:20:08+09:00",
      "last_checked": "2026-07-18T13:05:39+09:00",
      "status": "open",
      "transport_available": false,
      "science_only": false
    },
    "corp:95445:course:bg2So": {
      "url": "https://job.mynavi.jp/28/pc/corpinfo/displayInternship/index?corpId=95445&optNo=bg2So",
      "last_discovered": "2026-07-18T12:20:08+09:00",
      "last_checked": "2026-07-18T13:05:42+09:00",
      "status": "open",
      "transport_available": false,
      "science_only": false
    },
    "corp:460:course:YVizo": {
      "url": "https://job.mynavi.jp/28/pc/corpinfo/displayInternship/index?corpId=460&optNo=YVizo",
      "last_discovered": "2026-07-18T12:20:08+09:00",
      "last_checked": "2026-07-18T13:03:19+09:00",
      "status": "open",
      "transport_available": false,
      "science_only": false
    },
    "corp:84252:course:eF1b7": {
      "url": "https://job.mynavi.jp/28/pc/corpinfo/displayInternship/index?corpId=84252&optNo=eF1b7",
      "last_discovered": "2026-07-18T12:20:08+09:00",
      "last_checked": "2026-07-18T13:05:13+09:00",
      "status": "open",
      "transport_available": false,
      "science_only": false
    },
    "corp:70547:course:NPd7H": {
      "url": "https://job.mynavi.jp/28/pc/corpinfo/displayInternship/index?corpId=70547&optNo=NPd7H",
      "last_discovered": "2026-07-18T12:20:08+09:00",
      "last_checked": "2026-07-18T13:04:22+09:00",
      "status": "open",
      "transport_available": false,
      "science_only": false
    },
    "corp:70547:course:8wVPz": {
      "url": "https://job.mynavi.jp/28/pc/corpinfo/displayInternship/index?corpId=70547&optNo=8wVPz",
      "last_discovered": "2026-07-18T12:20:08+09:00",
      "last_checked": "2026-07-18T13:04:20+09:00",
      "status": "open",
      "transport_available": false,
      "science_only": false
    },
    "corp:70547:course:y4DHI": {
      "url": "https://job.mynavi.jp/28/pc/corpinfo/displayInternship/index?corpId=70547&optNo=y4DHI",
      "last_discovered": "2026-07-18T12:20:08+09:00",
      "last_checked": "2026-07-18T13:04:25+09:00",
      "status": "open",
      "transport_available": false,
      "science_only": false
    },
    "corp:56242:course:B5mkX": {
      "url": "https://job.mynavi.jp/28/pc/corpinfo/displayInternship/index?corpId=56242&optNo=B5mkX",
      "last_discovered": "2026-07-18T12:20:08+09:00",
      "last_checked": "2026-07-18T13:03:39+09:00",
      "status": "open",
      "transport_available": false,
      "science_only": false
    },
    "corp:56242:course:enghD": {
      "url": "https://job.mynavi.jp/28/pc/corpinfo/displayInternship/index?corpId=56242&optNo=enghD",
      "last_discovered": "2026-07-18T12:20:08+09:00",
      "last_checked": "2026-07-18T13:03:42+09:00",
      "status": "open",
      "transport_available": false,
      "science_only": false
    },
    "corp:239815:course:lZZes": {
      "url": "https://job.mynavi.jp/28/pc/corpinfo/displayInternship/index?corpId=239815&optNo=lZZes",
      "last_discovered": "2026-07-18T12:20:08+09:00",
      "last_checked": "2026-07-18T13:02:52+09:00",
      "status": "open",
      "transport_available": false,
      "science_only": false
    },
    "corp:532:course:iYmrI": {
      "url": "https://job.mynavi.jp/28/pc/corpinfo/displayInternship/index?corpId=532&optNo=iYmrI",
      "last_discovered": "2026-07-18T12:20:08+09:00",
      "last_checked": "2026-07-18T13:03:37+09:00",
      "status": "open",
      "transport_available": false,
      "science_only": false
    },
    "corp:532:course:XtoIp": {
      "url": "https://job.mynavi.jp/28/pc/corpinfo/displayInternship/index?corpId=532&optNo=XtoIp",
      "last_discovered": "2026-07-18T12:20:08+09:00",
      "last_checked": "2026-07-18T13:03:34+09:00",
      "status": "open",
      "transport_available": false,
      "science_only": false
    },
    "corp:532:course:eCnuo": {
      "url": "https://job.mynavi.jp/28/pc/corpinfo/displayInternship/index?corpId=532&optNo=eCnuo",
      "last_discovered": "2026-07-18T12:20:08+09:00",
      "last_checked": "2026-07-18T13:03:36+09:00",
      "status": "open",
      "transport_available": false,
      "science_only": true
    },
    "corp:59411:course:WUJ5l": {
      "url": "https://job.mynavi.jp/28/pc/corpinfo/displayInternship/index?corpId=59411&optNo=WUJ5l",
      "last_discovered": "2026-07-18T12:20:08+09:00",
      "last_checked": "2026-07-18T13:03:56+09:00",
      "status": "open",
      "transport_available": false,
      "science_only": false
    },
    "corp:109648:course:i3f4h": {
      "url": "https://job.mynavi.jp/28/pc/corpinfo/displayInternship/index?corpId=109648&optNo=i3f4h",
      "last_discovered": "2026-07-18T12:20:08+09:00",
      "last_checked": "2026-07-18T13:02:13+09:00",
      "status": "open",
      "transport_available": false,
      "science_only": false
    },
    "corp:74102:course:oQK01": {
      "url": "https://job.mynavi.jp/28/pc/corpinfo/displayInternship/index?corpId=74102&optNo=oQK01",
      "last_discovered": "2026-07-18T12:20:08+09:00",
      "last_checked": "2026-07-18T13:04:47+09:00",
      "status": "open",
      "transport_available": false,
      "science_only": false
    },
    "corp:70969:course:2U4JH": {
      "url": "https://job.mynavi.jp/28/pc/corpinfo/displayInternship/index?corpId=70969&optNo=2U4JH",
      "last_discovered": "2026-07-18T12:20:08+09:00",
      "last_checked": "2026-07-18T13:04:30+09:00",
      "status": "open",
      "transport_available": false,
      "science_only": false
    },
    "corp:70969:course:IGPAB": {
      "url": "https://job.mynavi.jp/28/pc/corpinfo/displayInternship/index?corpId=70969&optNo=IGPAB",
      "last_discovered": "2026-07-18T12:20:08+09:00",
      "last_checked": "2026-07-18T13:04:32+09:00",
      "status": "open",
      "transport_available": false,
      "science_only": false
    },
    "corp:70969:course:QDtCY": {
      "url": "https://job.mynavi.jp/28/pc/corpinfo/displayInternship/index?corpId=70969&optNo=QDtCY",
      "last_discovered": "2026-07-18T12:20:08+09:00",
      "last_checked": "2026-07-18T13:04:34+09:00",
      "status": "open",
      "transport_available": false,
      "science_only": false
    },
    "corp:98616:course:XCFSW": {
      "url": "https://job.mynavi.jp/28/pc/corpinfo/displayInternship/index?corpId=98616&optNo=XCFSW",
      "last_discovered": "2026-07-18T12:20:08+09:00",
      "last_checked": "2026-07-18T13:05:47+09:00",
      "status": "open",
      "transport_available": false,
      "science_only": false
    },
    "corp:201388:course:zy09y": {
      "url": "https://job.mynavi.jp/28/pc/corpinfo/displayInternship/index?corpId=201388&optNo=zy09y",
      "last_discovered": "2026-07-18T12:20:08+09:00",
      "last_checked": "2026-07-18T13:02:26+09:00",
      "status": "open",
      "transport_available": false,
      "science_only": true
    },
    "corp:72972:course:qf66B": {
      "url": "https://job.mynavi.jp/28/pc/corpinfo/displayInternship/index?corpId=72972&optNo=qf66B",
      "last_discovered": "2026-07-18T12:20:08+09:00",
      "last_checked": "2026-07-18T13:04:44+09:00",
      "status": "closed",
      "transport_available": false,
      "science_only": false
    },
    "corp:72972:course:ccuQI": {
      "url": "https://job.mynavi.jp/28/pc/corpinfo/displayInternship/index?corpId=72972&optNo=ccuQI",
      "last_discovered": "2026-07-18T12:20:08+09:00",
      "last_checked": "2026-07-18T13:04:42+09:00",
      "status": "closed",
      "transport_available": false,
      "science_only": false
    }
  }
}